[
  {
    "id": 1,
    "date": "12/05/2025",
    "team1players": ["Linus Kang"],
    "team2players": ["Aarnav Jay"],
    "points": [
      { "set": 1, "team1": 21, "team2": 18 },
      { "set": 2, "team1": 19, "team2": 21 },
      { "set": 3, "team1": 21, "team2": 17 }
    ],
    "status": "Completed",
    "winner": "team1",
    "umpire": "Derick Zeng",
    "matchtime": "00:42",
    "location": "goodminton"
  },
  {
    "id": 2,
    "date": "13/05/2025",
    "team1players": ["Ethan Wong"],
    "team2players": ["Kai Patel"],
    "points": [
      { "set": 1, "team1": 15, "team2": 21 },
      { "set": 2, "team1": 22, "team2": 20 },
      { "set": 3, "team1": 18, "team2": 21 }
    ],
    "status": "Completed",
    "winner": "team2",
    "umpire": "Sarah Lim",
    "matchtime": "00:38",
    "location": "goodminton"
  },
  {
    "id": 3,
    "date": "14/05/2025",
    "team1players": ["Olivia Tan"],
    "team2players": ["Noah Zhao"],
    "points": [
      { "set": 1, "team1": 21, "team2": 14 },
      { "set": 2, "team1": 21, "team2": 19 }
    ],
    "status": "Completed",
    "winner": "team1",
    "umpire": "Jason Liu",
    "matchtime": "00:29",
    "location": "smashzone"
  },
  {
    "id": 4,
    "date": "14/05/2025",
    "team1players": ["Lily Chen", "Marcus Ong"],
    "team2players": ["Sofia Lee", "Ryan Goh"],
    "points": [
      { "set": 1, "team1": 19, "team2": 21 },
      { "set": 2, "team1": 21, "team2": 12 },
      { "set": 3, "team1": 20, "team2": 22 }
    ],
    "status": "Completed",
    "winner": "team2",
    "umpire": "Emily Zhang",
    "matchtime": "00:50",
    "location": "goodminton"
  },
  {
    "id": 5,
    "date": "15/05/2025",
    "team1players": ["Ava Lim"],
    "team2players": ["Lucas Tan"],
    "points": [
      { "set": 1, "team1": 21, "team2": 9 },
      { "set": 2, "team1": 21, "team2": 11 }
    ],
    "status": "Completed",
    "winner": "team1",
    "umpire": "Tommy Yap",
    "matchtime": "00:25",
    "location": "northcourt"
  },
  {
    "id": 6,
    "date": "15/05/2025",
    "team1players": ["Chloe Sim"],
    "team2players": ["Nathan Foo"],
    "points": [
      { "set": 1, "team1": 21, "team2": 23 },
      { "set": 2, "team1": 21, "team2": 18 },
      { "set": 3, "team1": 21, "team2": 19 }
    ],
    "status": "Completed",
    "winner": "team1",
    "umpire": "Zac Teo",
    "matchtime": "00:47",
    "location": "smashzone"
  },
  {
    "id": 7,
    "date": "16/05/2025",
    "team1players": ["Isaac Lee", "Jamie Koh"],
    "team2players": ["Mia Tan", "Felix Goh"],
    "points": [
      { "set": 1, "team1": 17, "team2": 21 },
      { "set": 2, "team1": 21, "team2": 19 },
      { "set": 3, "team1": 21, "team2": 13 }
    ],
    "status": "Completed",
    "winner": "team1",
    "umpire": "Celine Ng",
    "matchtime": "00:53",
    "location": "southhall"
  },
  {
    "id": 8,
    "date": "17/05/2025",
    "team1players": ["Zoe Chua"],
    "team2players": ["Leo Chan"],
    "points": [
      { "set": 1, "team1": 19, "team2": 21 },
      { "set": 2, "team1": 15, "team2": 21 }
    ],
    "status": "Completed",
    "winner": "team2",
    "umpire": "Kiran Singh",
    "matchtime": "00:31",
    "location": "goodminton"
  },
  {
    "id": 9,
    "date": "18/05/2025",
    "team1players": ["Harper Yeo", "Zachary Lim"],
    "team2players": ["Emily Tan", "Adam Goh"],
    "points": [
      { "set": 1, "team1": 21, "team2": 17 },
      { "set": 2, "team1": 16, "team2": 21 },
      { "set": 3, "team1": 18, "team2": 21 }
    ],
    "status": "Completed",
    "winner": "team2",
    "umpire": "Noel Ong",
    "matchtime": "00:48",
    "location": "eastcourt"
  },
  {
    "id": 10,
    "date": "18/05/2025",
    "team1players": ["Sienna Koh"],
    "team2players": ["Matthew Chan"],
    "points": [
      { "set": 1, "team1": 20, "team2": 22 },
      { "set": 2, "team1": 21, "team2": 17 },
      { "set": 3, "team1": 21, "team2": 19 }
    ],
    "status": "Completed",
    "winner": "team1",
    "umpire": "Vanessa Tay",
    "matchtime": "00:41",
    "location": "goodminton"
  },
  {
    "id": 11,
    "date": "19/05/2025",
    "team1players": ["Ben Ho"],
    "team2players": ["Avery Leong"],
    "points": [
      { "set": 1, "team1": 21, "team2": 19 },
      { "set": 2, "team1": 14, "team2": 21 },
      { "set": 3, "team1": 19, "team2": 21 }
    ],
    "status": "Completed",
    "winner": "team2",
    "umpire": "Darren Seet",
    "matchtime": "00:45",
    "location": "smashzone"
  }
]